{
  "id": 240,
  "letters": [
    "R",
    "T",
    "F",
    "H",
    "A",
    "E"
  ],
  "words": [
    {
      "word": "FATHER",
      "row": 2,
      "col": 0,
      "dir": "across",
      "def": "a male parent (also used as a term of address to your father)",
      "zh": "n. 父親, 祖先, 長輩, 神父, 創始者"
    },
    {
      "word": "AFTER",
      "row": 2,
      "col": 1,
      "dir": "down",
      "def": "located farther aft",
      "zh": "prep. 在...之後, 由於"
    },
    {
      "word": "HEART",
      "row": 5,
      "col": 0,
      "dir": "across",
      "def": "the locus of feelings and intuitions",
      "zh": "n. 心, 心臟, 中心, 內心, 感情, 精神, 心情, 寶貝兒"
    },
    {
      "word": "ARE",
      "row": 4,
      "col": 3,
      "dir": "down",
      "def": "a unit of surface area equal to 100 square meters",
      "zh": "be的現在時複數或第二人稱單數"
    },
    {
      "word": "FAR",
      "row": 0,
      "col": 5,
      "dir": "down",
      "def": "a terrorist organization that seeks to overthrow the government dominated by Tutsi and to institute Hutu control again",
      "zh": "a. 遠的, 久遠的, 遙遠的"
    }
  ],
  "bonus": [
    "AFT",
    "ARF",
    "ART",
    "ATE",
    "EAR",
    "EAT",
    "EFT",
    "ERA",
    "ETA",
    "ETH",
    "FAT",
    "FEH",
    "FER",
    "FET",
    "HAE",
    "HAT",
    "HER",
    "HET",
    "RAH",
    "RAT",
    "REF",
    "RET",
    "TAE",
    "TAR",
    "TEA",
    "THE",
    "EATH",
    "FARE",
    "FART",
    "FATE",
    "FEAR",
    "FEAT",
    "FETA",
    "FRAE",
    "FRAT",
    "FRET",
    "HAET",
    "HAFT",
    "HARE",
    "HART",
    "HATE",
    "HEAR",
    "HEAT",
    "HEFT",
    "RAFT",
    "RATE",
    "RATH",
    "REFT",
    "RHEA",
    "TAHR",
    "TARE",
    "TEAR",
    "THAE",
    "TREF",
    "EARTH",
    "HATER",
    "RATHE",
    "HAFTER",
    "TREFAH"
  ]
}
